LICENSE
README.md
pyproject.toml
agentpay_client/__init__.py
agentpay_client-0.0.1.dev0.dist-info/METADATA
agentpay_client-0.0.1.dev0.dist-info/WHEEL
agentpay_client-0.0.1.dev0.dist-info/licenses/LICENSE
agentpay_client-0.0.1.dev0.dist-info/RECORD
